{
  "source_file": "/home/jc/Videos/ai_ocr/samples/bank_stmt.pdf",
  "engine": "nanonets",
  "timestamp": "2026-01-14T14:49:50.599026",
  "processing_time_seconds": 366.29,
  "text": "\n--- Page 1 ---\n320/W/0939\n\n```html\n<header>\nOCBC Bank\n65 Chulla Street, OCBC Centre\nSingapore 049513\n</header>\n\n<page_number>Page 1 of 2</page_number>\n\n**STATEMENT OF ACCOUNT**\n\nFor enquiries, please call\nBusiness Banking at 6536 1111\n\nOCBC North Branch\n\nAP HOUSE PTE. LTD.\n400 ORCHARD ROAD\n#04-07\nORCHARD TOWERS\nSINGAPORE 238875\n\n<page_number>Page 1 of 2</page_number>\n\n**STATEMENT OF ACCOUNT**\n\nFor enquiries, please call\nBusiness Banking at 6536 1111\n\nOCBC North Branch\n\n**SGD BUSINESS ACCOUNT**\n\nAccount No. 641980588001\n\n<table>\n  <thead>\n    <tr>\n      <th rowspan=\"2\">Transaction</th>\n      <th rowspan=\"2\">Value</th>\n      <th rowspan=\"2\">Transaction Date</th>\n      <th rowspan=\"2\">Date d.A.T. B</th>\n      <th rowspan=\"2\">Description</th>\n      <th rowspan=\"2\">Cheque</th>\n      <th rowspan=\"2\">Withdrawal</th>\n      <th colspan=\"2\">Deposit</th>\n      <th rowspan=\"2\">Balance</th>\n    </tr>\n    <tr>\n      <th>Notes</th>\n    </tr>\n    <tr>\n      <th></th>\n      <th></th>\n      <th>Date d.A.T. B</th>\n      <th></th>\n      <th></th>\n      <th></th>\n      <th></th>\n      <th></th>\n      <th></th>\n      <th></th>\n    </tr>\n  </thead>\n  <tbody>\n    <tr>\n      <td></td>\n      <td></td>\n      <td></td>\n      <td></td>\n      <td></td>\n      <td>BALANCE B/F</td>\n      <td></td>\n      <td></td>\n      <td></td>\n      <td>2,376.34</td>\n    </tr>\n    <tr>\n      <td></td>\n      <td></td>\n      <td></td>\n      <td></td>\n      <td></td>\n      <td></td>\n      <td></td>\n      <td></td>\n      <td></td>\n      <td>2,370.14</td>\n    </tr>\n    <tr>\n      <td></td>\n      <td></td>\n      <td></td>\n      <td></td>\n      <td></td>\n      <td></td>\n      <td></td>\n      <td></td>\n      <td></td>\n      <td>2,370.02</td>\n    </tr>\n    <tr>\n      <td></td>\n      <td></td>\n      <td></td>\n      <td></td>\n      <td></td>\n      <td></td>\n      <td></td>\n      <td></td>\n      <td></td>\n      <td>1,600.02</td>\n    </tr>\n    <tr>\n      <td></td>\n      <td></td>\n      <td></td>\n      <td></td>\n      <td></td>\n      <td></td>\n      <td></td>\n      <td></td>\n      <td></td>\n      <td>1,600.42</td>\n    </tr>\n    <tr>\n      <td></td>\n      <td></td>\n      <td></td>\n      <td></td>\n      <td></td>\n      <td></td>\n      <td></td>\n      <td></td>\n      <td></td>\n      <td>1,600.22</td>\n    </tr>\n    <tr>\n      <td></td>\n      <td></td>\n      <td></td>\n      <td></td>\n      <td></td>\n      <td></td>\n      <td></td>\n      <td></td>\n      <td></td>\n      <td>1,600.22</td>\n    </tr>\n    <tr>\n      <td></td>\n      <td></td>\n      <td></td>\n      <td></td>\n      <td></td>\n      <td></td>\n      <td></td>\n      <td></td>\n      <td></td>\n      <td>1,60"
}